{
  "observer": "area51-reachability",
  "date_utc": "2026-07-20",
  "data_status": "partial",
  "bucket_minutes": 15,
  "bbox": {
    "min_lat": 35.0,
    "max_lat": 39.0,
    "min_lon": -118.5,
    "max_lon": -112.5
  },
  "bucket_count": 1,
  "au": {
    "janet_like": 41,
    "other": 19,
    "total": 60
  },
  "baseline_30d": {
    "janet_like": {
      "mean": 86.4091,
      "std": 112.8433,
      "effective_std": 112.8433
    },
    "other": {
      "mean": 34.5455,
      "std": 50.9525,
      "effective_std": 50.9525
    },
    "total": {
      "mean": 120.9545,
      "std": 163.5716,
      "effective_std": 163.5716
    }
  },
  "significance": {
    "sigma_mult": 2.0,
    "janet_like": {
      "is_significant": false,
      "z": -0.4024
    },
    "other": {
      "is_significant": false,
      "z": -0.3051
    },
    "total": {
      "is_significant": false,
      "z": -0.3726
    },
    "any_significant": false
  },
  "diagnostics": {
    "api_attempts": 1,
    "retries": 0,
    "http_status": 200,
    "endpoint": "https://opensky-network.org/api/states/all?lamin=35.0&lamax=39.0&lomin=-118.5&lomax=-112.5",
    "last_error": null
  }
}
