{
  "availability": "instock",
  "average_30d": 9.99,
  "average_365d": 9.99,
  "category": "society",
  "currency": "EUR",
  "current_price": 9.99,
  "data_status": "ok",
  "date": "2026-07-23",
  "date_utc": "2026-07-23",
  "description": "Tracks the retail price development of a representative 500 g loose East Frisian black tea product over time. The observer is descriptive only and does not rate brands or product quality.",
  "diagnostics": {
    "api_attempts": 1,
    "availability": "instock",
    "brand": "Bünting Tee",
    "category": "Ostfriesentee",
    "currency": "EUR",
    "ean": "4008837201054",
    "fetch_url": "https://www.combi.de/buenting_tee_gruenpack_1101010007.html",
    "fetched_at_utc": "2026-07-23T06:06:09.003659+00:00",
    "http_status": 200,
    "meta_fields_present": [
      "product:availability",
      "product:brand",
      "product:category",
      "product:condition",
      "product:ean",
      "product:is_product_shareable",
      "product:price:amount",
      "product:price:currency"
    ],
    "parse_status": "parsed_meta_tags",
    "retries": 0,
    "source": "combi_product_meta"
  },
  "display_name": "East Frisian Tea Observer",
  "ean": "4008837201054",
  "historical_max": 9.99,
  "historical_min": 9.98,
  "history": [
    {
      "date": "2026-06-30",
      "source": "manual_seed",
      "value": 9.98
    },
    {
      "date": "2026-07-01",
      "source": "combi_product_meta",
      "value": 9.99
    },
    {
      "date": "2026-07-03",
      "source": "combi_product_meta",
      "value": 9.99
    },
    {
      "date": "2026-07-04",
      "source": "combi_product_meta",
      "value": 9.99
    },
    {
      "date": "2026-07-05",
      "source": "combi_product_meta",
      "value": 9.99
    },
    {
      "date": "2026-07-06",
      "source": "combi_product_meta",
      "value": 9.99
    },
    {
      "date": "2026-07-07",
      "source": "combi_product_meta",
      "value": 9.99
    },
    {
      "date": "2026-07-08",
      "source": "combi_product_meta",
      "value": 9.99
    },
    {
      "date": "2026-07-09",
      "source": "combi_product_meta",
      "value": 9.99
    },
    {
      "date": "2026-07-10",
      "source": "combi_product_meta",
      "value": 9.99
    },
    {
      "date": "2026-07-11",
      "source": "combi_product_meta",
      "value": 9.99
    },
    {
      "date": "2026-07-12",
      "source": "combi_product_meta",
      "value": 9.99
    },
    {
      "date": "2026-07-13",
      "source": "combi_product_meta",
      "value": 9.99
    },
    {
      "date": "2026-07-14",
      "source": "combi_product_meta",
      "value": 9.99
    },
    {
      "date": "2026-07-15",
      "source": "combi_product_meta",
      "value": 9.99
    },
    {
      "date": "2026-07-16",
      "source": "combi_product_meta",
      "value": 9.99
    },
    {
      "date": "2026-07-17",
      "source": "combi_product_meta",
      "value": 9.99
    },
    {
      "date": "2026-07-18",
      "source": "combi_product_meta",
      "value": 9.99
    },
    {
      "date": "2026-07-19",
      "source": "combi_product_meta",
      "value": 9.99
    },
    {
      "date": "2026-07-20",
      "source": "combi_product_meta",
      "value": 9.99
    },
    {
      "date": "2026-07-21",
      "source": "combi_product_meta",
      "value": 9.99
    },
    {
      "date": "2026-07-22",
      "source": "combi_product_meta",
      "value": 9.99
    },
    {
      "date": "2026-07-23",
      "source": "combi_product_meta",
      "value": 9.99
    }
  ],
  "observed_changes": [
    "Price is unchanged compared with the previous observation."
  ],
  "observer": "east-frisian-tea-prices",
  "record_high": 9.99,
  "record_low": 9.98,
  "source": "combi_product_meta",
  "source_url": "https://www.combi.de/buenting_tee_gruenpack_1101010007.html",
  "status": "ok",
  "trend_delta": 0.0,
  "trend_delta_percent": 0.0,
  "unit": "EUR per 500 g loose tea"
}
