{
  "last_run_utc": "2026-07-16T06:07:45.606403+00:00",
  "latest_date_utc": "2026-07-16",
  "last_7_days": [
    {
      "date_utc": "2026-07-10",
      "any_significant": false
    },
    {
      "date_utc": "2026-07-11",
      "any_significant": false
    },
    {
      "date_utc": "2026-07-12",
      "any_significant": false
    },
    {
      "date_utc": "2026-07-13",
      "any_significant": false
    },
    {
      "date_utc": "2026-07-14",
      "any_significant": false
    },
    {
      "date_utc": "2026-07-15",
      "any_significant": false
    },
    {
      "date_utc": "2026-07-16",
      "any_significant": false
    }
  ],
  "last_daily_run_utc": "2026-07-16T06:07:49Z",
  "run_date_utc": "2026-07-16",
  "runner": "scripts/run_daily_cron.py"
}
