{
  "observer": "cuba-internet-weather",
  "timestamp": "2026-02-25T02:14:54.590316+00:00",
  "targets": [
    {
      "name": "Cuba government portal",
      "host": "www.cuba.cu",
      "ping": {
        "sent": 4,
        "received": 0,
        "loss_percent": 100.0,
        "rtt_min_ms": null,
        "rtt_avg_ms": null,
        "rtt_max_ms": null,
        "error": "Ping failed"
      },
      "tcp_443": {
        "ok": false,
        "connect_ms": null,
        "error": "[Errno 111] Connection refused"
      },
      "dns": {
        "a": {
          "status": "answer",
          "query_ms": 4.38,
          "error": null
        }
      }
    },
    {
      "name": "ETECSA",
      "host": "www.etecsa.cu",
      "ping": {
        "sent": 4,
        "received": 4,
        "loss_percent": 0.0,
        "rtt_min_ms": 374.379,
        "rtt_avg_ms": 573.029,
        "rtt_max_ms": 727.391,
        "error": null
      },
      "tcp_443": {
        "ok": true,
        "connect_ms": 670.26,
        "error": null
      },
      "dns": {
        "a": {
          "status": "answer",
          "query_ms": 3.28,
          "error": null
        }
      }
    },
    {
      "name": "Granma",
      "host": "www.granma.cu",
      "ping": {
        "sent": 4,
        "received": 4,
        "loss_percent": 0.0,
        "rtt_min_ms": 178.137,
        "rtt_avg_ms": 238.816,
        "rtt_max_ms": 287.312,
        "error": null
      },
      "tcp_443": {
        "ok": true,
        "connect_ms": 1011.21,
        "error": null
      },
      "dns": {
        "a": {
          "status": "answer",
          "query_ms": 2.95,
          "error": null
        }
      }
    },
    {
      "name": "Cubadebate",
      "host": "www.cubadebate.cu",
      "ping": {
        "sent": 4,
        "received": 0,
        "loss_percent": 100.0,
        "rtt_min_ms": null,
        "rtt_avg_ms": null,
        "rtt_max_ms": null,
        "error": "Ping failed"
      },
      "tcp_443": {
        "ok": true,
        "connect_ms": 572.96,
        "error": null
      },
      "dns": {
        "a": {
          "status": "answer",
          "query_ms": 5.33,
          "error": null
        }
      }
    },
    {
      "name": "Juventud Rebelde",
      "host": "www.juventudrebelde.cu",
      "ping": {
        "sent": 4,
        "received": 4,
        "loss_percent": 0.0,
        "rtt_min_ms": 516.962,
        "rtt_avg_ms": 582.538,
        "rtt_max_ms": 670.227,
        "error": null
      },
      "tcp_443": {
        "ok": true,
        "connect_ms": 1584.79,
        "error": null
      },
      "dns": {
        "a": {
          "status": "answer",
          "query_ms": 3.71,
          "error": null
        }
      }
    },
    {
      "name": "Radio Habana Cuba",
      "host": "www.radiohc.cu",
      "ping": {
        "sent": 4,
        "received": 4,
        "loss_percent": 0.0,
        "rtt_min_ms": 373.912,
        "rtt_avg_ms": 669.115,
        "rtt_max_ms": 988.86,
        "error": null
      },
      "tcp_443": {
        "ok": true,
        "connect_ms": 551.93,
        "error": null
      },
      "dns": {
        "a": {
          "status": "answer",
          "query_ms": 3.8,
          "error": null
        }
      }
    }
  ],
  "weather_summary": {
    "classification": "degraded",
    "reason": "High packet loss or elevated latency detected."
  },
  "notes": "Passive measurement of packet loss, TCP 443 handshake, and DNS A lookups for Cuba. Values represent point-in-time signals only.",
  "data_status": "ok",
  "diagnostics": {
    "api_attempts": 0,
    "retries": 0,
    "http_status": null
  }
}
