{"data_status":"ok","diagnostics":{"api_attempts":0,"http_status":null,"retries":0},"notes":"Passive measurement of packet loss, TCP 443 handshake, and DNS A lookups for Cuba. Values represent point-in-time signals only.","observer":"cuba-internet-weather","targets":[{"dns":{"a":{"error":null,"query_ms":988.83,"status":"answer"}},"host":"www.cuba.cu","name":"Cuba government portal","ping":{"error":"Ping failed","loss_percent":100.0,"received":0,"rtt_avg_ms":null,"rtt_max_ms":null,"rtt_min_ms":null,"sent":4},"tcp_443":{"connect_ms":null,"error":"timed out","ok":false}},{"dns":{"a":{"error":null,"query_ms":159.92,"status":"answer"}},"host":"www.etecsa.cu","name":"ETECSA","ping":{"error":null,"loss_percent":0.0,"received":4,"rtt_avg_ms":164.421,"rtt_max_ms":164.508,"rtt_min_ms":164.277,"sent":4},"tcp_443":{"connect_ms":333.91,"error":null,"ok":true}},{"dns":{"a":{"error":null,"query_ms":330.38,"status":"answer"}},"host":"www.granma.cu","name":"Granma","ping":{"error":null,"loss_percent":0.0,"received":4,"rtt_avg_ms":16.862,"rtt_max_ms":16.931,"rtt_min_ms":16.777,"sent":4},"tcp_443":{"connect_ms":355.87,"error":null,"ok":true}},{"dns":{"a":{"error":null,"query_ms":8.74,"status":"answer"}},"host":"www.cubadebate.cu","name":"Cubadebate","ping":{"error":"Ping failed","loss_percent":100.0,"received":0,"rtt_avg_ms":null,"rtt_max_ms":null,"rtt_min_ms":null,"sent":4},"tcp_443":{"connect_ms":330.61,"error":null,"ok":true}},{"dns":{"a":{"error":null,"query_ms":342.11,"status":"answer"}},"host":"www.juventudrebelde.cu","name":"Juventud Rebelde","ping":{"error":null,"loss_percent":0.0,"received":4,"rtt_avg_ms":16.833,"rtt_max_ms":16.911,"rtt_min_ms":16.784,"sent":4},"tcp_443":{"connect_ms":1038.34,"error":null,"ok":true}},{"dns":{"a":{"error":null,"query_ms":510.76,"status":"answer"}},"host":"www.radiohc.cu","name":"Radio Habana Cuba","ping":{"error":null,"loss_percent":0.0,"received":4,"rtt_avg_ms":164.542,"rtt_max_ms":164.699,"rtt_min_ms":164.274,"sent":4},"tcp_443":{"connect_ms":644.58,"error":null,"ok":true}}],"timestamp":"2026-07-17T06:05:59.822642+00:00","weather_summary":{"classification":"degraded","reason":"High packet loss or elevated latency detected."}}
