{"data_status":"ok","diagnostics":{"api_attempts":0,"http_status":null,"retries":0},"notes":"Passive measurement of packet loss, TCP 443 handshake, and DNS A lookups for Cuba. Values represent point-in-time signals only.","observer":"cuba-internet-weather","targets":[{"dns":{"a":{"error":null,"query_ms":406.84,"status":"answer"}},"host":"www.cuba.cu","name":"Cuba government portal","ping":{"error":"Ping failed","loss_percent":100.0,"received":0,"rtt_avg_ms":null,"rtt_max_ms":null,"rtt_min_ms":null,"sent":4},"tcp_443":{"connect_ms":null,"error":"timed out","ok":false}},{"dns":{"a":{"error":null,"query_ms":191.14,"status":"answer"}},"host":"www.etecsa.cu","name":"ETECSA","ping":{"error":null,"loss_percent":0.0,"received":4,"rtt_avg_ms":170.101,"rtt_max_ms":173.13,"rtt_min_ms":168.217,"sent":4},"tcp_443":{"connect_ms":364.4,"error":null,"ok":true}},{"dns":{"a":{"error":null,"query_ms":730.1,"status":"answer"}},"host":"www.granma.cu","name":"Granma","ping":{"error":null,"loss_percent":0.0,"received":4,"rtt_avg_ms":16.885,"rtt_max_ms":17.087,"rtt_min_ms":16.707,"sent":4},"tcp_443":{"connect_ms":704.89,"error":null,"ok":true}},{"dns":{"a":{"error":null,"query_ms":11.24,"status":"answer"}},"host":"www.cubadebate.cu","name":"Cubadebate","ping":{"error":"Ping failed","loss_percent":100.0,"received":0,"rtt_avg_ms":null,"rtt_max_ms":null,"rtt_min_ms":null,"sent":4},"tcp_443":{"connect_ms":183.25,"error":null,"ok":true}},{"dns":{"a":{"error":null,"query_ms":9.78,"status":"answer"}},"host":"www.juventudrebelde.cu","name":"Juventud Rebelde","ping":{"error":null,"loss_percent":0.0,"received":4,"rtt_avg_ms":16.905,"rtt_max_ms":17.001,"rtt_min_ms":16.817,"sent":4},"tcp_443":{"connect_ms":386.54,"error":null,"ok":true}},{"dns":{"a":{"error":null,"query_ms":547.78,"status":"answer"}},"host":"www.radiohc.cu","name":"Radio Habana Cuba","ping":{"error":null,"loss_percent":0.0,"received":4,"rtt_avg_ms":175.632,"rtt_max_ms":176.009,"rtt_min_ms":175.371,"sent":4},"tcp_443":{"connect_ms":527.03,"error":null,"ok":true}}],"timestamp":"2026-07-13T06:06:04.891050+00:00","weather_summary":{"classification":"degraded","reason":"High packet loss or elevated latency detected."}}
