{"data_status":"partial","diagnostics":{"api_attempts":20,"http_status":null,"no_nameservers":0,"retries":0,"servfail":0},"notes":"Queries are performed with standard recursion via the system resolver. No censorship circumvention or evasion techniques are used.","observer":"iran-dns-behavior","status":"ok","summary":{"answered":19,"errors":0,"no_nameservers":0,"refused":0,"servfail":0,"timeouts":0,"total_queries":20},"targets":[{"domain":"example.com","name":"IANA Example","queries":{"A":{"answer_count":2,"error":null,"query_ms":9.46,"status":"answer"},"AAAA":{"answer_count":2,"error":null,"query_ms":8.68,"status":"answer"},"MX":{"answer_count":1,"error":null,"query_ms":9.91,"status":"answer"},"TXT":{"answer_count":2,"error":null,"query_ms":11.91,"status":"answer"}}},{"domain":"iana.org","name":"IANA Root","queries":{"A":{"answer_count":1,"error":null,"query_ms":8.6,"status":"answer"},"AAAA":{"answer_count":1,"error":null,"query_ms":9.36,"status":"answer"},"MX":{"answer_count":4,"error":null,"query_ms":18.26,"status":"answer"},"TXT":{"answer_count":11,"error":null,"query_ms":43.99,"status":"answer"}}},{"domain":"wikipedia.org","name":"Wikipedia","queries":{"A":{"answer_count":1,"error":null,"query_ms":8.22,"status":"answer"},"AAAA":{"answer_count":1,"error":null,"query_ms":8.65,"status":"answer"},"MX":{"answer_count":2,"error":null,"query_ms":8.45,"status":"answer"},"TXT":{"answer_count":3,"error":null,"query_ms":16.84,"status":"answer"}}},{"domain":"github.com","name":"GitHub","queries":{"A":{"answer_count":1,"error":null,"query_ms":8.1,"status":"answer"},"AAAA":{"answer_count":0,"error":null,"query_ms":8.58,"status":"noanswer"},"MX":{"answer_count":1,"error":null,"query_ms":10.14,"status":"answer"},"TXT":{"answer_count":22,"error":null,"query_ms":31.67,"status":"answer"}}},{"domain":"cloudflare.com","name":"Cloudflare","queries":{"A":{"answer_count":2,"error":null,"query_ms":8.54,"status":"answer"},"AAAA":{"answer_count":2,"error":null,"query_ms":8.29,"status":"answer"},"MX":{"answer_count":4,"error":null,"query_ms":8.78,"status":"answer"},"TXT":{"answer_count":26,"error":null,"query_ms":32.61,"status":"answer"}}}],"timestamp":"2026-07-19T06:06:21.601753+00:00"}
